[
  {
    "path": "/adichev17/WardrobeApp-ASP-MVC/tree/master/Models",
    "title": "WardrobeApp-ASP-MVC/Models at master 路 adichev17/WardrobeApp-ASP-MVC",
    "count": 6,
    "uniques": 1
  },
  {
    "path": "/adichev17/WardrobeApp-ASP-MVC/tree/master/Views",
    "title": "WardrobeApp-ASP-MVC/Views at master 路 adichev17/WardrobeApp-ASP-MVC",
    "count": 3,
    "uniques": 1
  },
  {
    "path": "/adichev17/WardrobeApp-ASP-MVC/tree/master/Manager",
    "title": "WardrobeApp-ASP-MVC/Manager at master 路 adichev17/WardrobeApp-ASP-MVC",
    "count": 2,
    "uniques": 1
  },
  {
    "path": "/adichev17/WardrobeApp-ASP-MVC/tree/master/Models/ClothingSeason",
    "title": "WardrobeApp-ASP-MVC/Models/ClothingSeason at master 路 adichev17/WardrobeApp-A...",
    "count": 2,
    "uniques": 1
  },
  {
    "path": "/adichev17/WardrobeApp-ASP-MVC",
    "title": "adichev17/WardrobeApp-ASP-MVC: Mobile application for wardrobe introduction",
    "count": 1,
    "uniques": 1
  }
]